domain_scan/__init__.py
domain_scan-0.1.0.dev0.data/scripts/gather
domain_scan-0.1.0.dev0.data/scripts/scan
domain_scan-0.1.0.dev0.dist-info/DESCRIPTION.rst
domain_scan-0.1.0.dev0.dist-info/METADATA
domain_scan-0.1.0.dev0.dist-info/RECORD
domain_scan-0.1.0.dev0.dist-info/WHEEL
domain_scan-0.1.0.dev0.dist-info/metadata.json
domain_scan-0.1.0.dev0.dist-info/top_level.txt
