Metadata-Version: 2.0
Name: domain-scan
Version: 0.1.0.dev0
Summary: lightweight scan pipeline for orchestrating third party tools, at scale and (optionally) using serverless infrastructure
Home-page: https://18f.gsa.gov
Author: GSA 18F
Author-email: pulse@cio.gov
License: License :: CC0 1.0 Universal (CC0 1.0) Public Domain Dedication
Download-URL: https://github.com/18F/domain-scan
Keywords: https best practices web-crawling domain scanning
Platform: UNKNOWN
Classifier: Development Status :: 4 - Beta
Classifier: Intended Audience :: Developers
Classifier: License :: CC0 1.0 Universal (CC0 1.0) Public Domain Dedication
Classifier: Programming Language :: Python :: 2
Classifier: Programming Language :: Python :: 2.7
Classifier: Programming Language :: Python :: 3
Classifier: Programming Language :: Python :: 3.4
Classifier: Programming Language :: Python :: 3.5
Classifier: Programming Language :: Python :: 3.6
Provides-Extra: test
Requires-Dist: strict-rfc3339
Requires-Dist: publicsuffix
Requires-Dist: boto3
Requires-Dist: ipython
Requires-Dist: sslyze (<1.4.0,>=1.3.4)
Requires-Dist: cryptography
Requires-Dist: pyyaml
Requires-Dist: requests
Requires-Dist: google-cloud-bigquery
Requires-Dist: google-auth-oauthlib
Provides-Extra: test
Requires-Dist: pytest; extra == 'test'
